enginecon/__init__.py
enginecon/base.py
enginecon/ie2111.py
enginecon/interestTableFunctions.py
enginecon/monteCarlo.py
enginecon/tax.py
enginecon/tornado.py
tests/__init__.py
tests/context.py
tests/test_interestTables.py
tests/test_monteCarlo.py
enginEcon-0.0.1.dist-info/LICENSE.txt
enginEcon-0.0.1.dist-info/METADATA
enginEcon-0.0.1.dist-info/WHEEL
enginEcon-0.0.1.dist-info/top_level.txt
enginEcon-0.0.1.dist-info/RECORD
